{
  "generated_at": "2026-01-29T16:02:09.075311+08:00",
  "total_titles_processed": 1477,
  "failed_sources": [],
  "trends": [
    {
      "keyword_group": "小米 特斯拉 华为",
      "match_count": 45,
      "titles": [
        {
          "title": "美股期指走高 美联储决议来袭 微软、Meta和特斯拉盘后公布财报 | 今夜看点",
          "url": "https://www.cls.cn/detail/2273158",
          "source": "财联社热门",
          "ranks": [
            11,
            10,
            13
          ],
          "is_new": false,
          "appearance_count": 16,
          "time_info": "[00时37分 ~ 09时59分]"
        },
        {
          "title": "特斯拉电话会：停产Model S/X全力转向AI，本季度发布第三代Optimus，今年是资本开支大年",
          "url": "https://wallstreetcn.com/articles/3764410",
          "source": "华尔街见闻",
          "ranks": [
            7,
            6
          ],
          "is_new": false,
          "appearance_count": 8,
          "time_info": "[09时59分 ~ 16时02分]"
        },
        {
          "title": "特斯拉营收下滑 盘后涨超3%",
          "url": "https://flash.jin10.com/detail/20260129061942377800",
          "source": "金十数据",
          "ranks": [
            1
          ],
          "is_new": false,
          "appearance_count": 3,
          "time_info": "[06时26分 ~ 06时55分]"
        },
        {
          "title": "特斯拉(TSLA.O)：MEGAPACK 3 也计划于2026年投入量产。",
          "url": "https://flash.jin10.com/detail/20260129051331631800",
          "source": "金十数据",
          "ranks": [
            5
          ],
          "is_new": false,
          "appearance_count": 3,
          "time_info": "[05时29分 ~ 05时56分]"
        },
        {
          "title": "特斯拉首席财务官：在动用内部资源后，公司可能会通过更多债务或其他方式为资本支出融资。",
          "url": "https://flash.jin10.com/detail/20260129072223309800",
          "source": "金十数据",
          "ranks": [
            2
          ],
          "is_new": false,
          "appearance_count": 2,
          "time_info": "[07时27分 ~ 07时50分]"
        },
        {
          "title": "特斯拉首席财务官：随着Optimus的生产和扩张启动，资本支出正投入计算领域，用于训练Optimus。",
          "url": "https://flash.jin10.com/detail/20260129072032917800",
          "source": "金十数据",
          "ranks": [
            3
          ],
          "is_new": false,
          "appearance_count": 2,
          "time_info": "[07时27分 ~ 07时50分]"
        },
        {
          "title": "财联社1月29日电，特斯拉表示已于1月16日签署协议，投资约20亿美元收购xAI的优先股。",
          "url": "https://api3.cls.cn/share/article/2273387?os=web&sv=8.4.6&app=CailianpressWeb",
          "source": "财联社电报",
          "ranks": [
            3,
            10,
            18
          ],
          "is_new": false,
          "appearance_count": 5,
          "time_info": "[05时55分 ~ 06时55分]"
        },
        {
          "title": "财联社1月29日电，财报公布后，Meta在法兰克福市场股价上涨6.9%；特斯拉股价在法兰克福盘前上涨1.8%。",
          "url": "https://api3.cls.cn/share/article/2273994?os=web&sv=8.4.6&app=CailianpressWeb",
          "source": "财联社电报",
          "ranks": [
            3
          ],
          "is_new": false,
          "appearance_count": 1,
          "time_info": "15时14分"
        },
        {
          "title": "纳斯达克金龙中国指数初步收涨0.3%。 热门中概股里，新东方初步收涨4.9%，比亚迪、理想涨超2%，阿里、网易、小米、美团涨超1%，蔚来跌超0.7%，文远知行跌1.9%，拼多多跌3.8%。 ETF中，CQQQ涨0.1%，KWEB涨0.5%。",
          "url": "https://wallstreetcn.com/livenews/3045827",
          "source": "华尔街见闻-快讯",
          "ranks": [
            3
          ],
          "is_new": false,
          "appearance_count": 1,
          "time_info": "05时29分"
        },
        {
          "title": "财联社1月29日电，加通贝祥将特斯拉目标价从551美元下调至520美元。",
          "url": "https://api3.cls.cn/share/article/2273989?os=web&sv=8.4.6&app=CailianpressWeb",
          "source": "财联社电报",
          "ranks": [
            5
          ],
          "is_new": false,
          "appearance_count": 1,
          "time_info": "15时14分"
        },
        {
          "title": "财联社1月29日电，特斯拉首席执行官马斯克表示，预计新款Roadster车型将于4月首次亮相。",
          "url": "https://api3.cls.cn/share/article/2273417?os=web&sv=8.4.6&app=CailianpressWeb",
          "source": "财联社电报",
          "ranks": [
            2,
            17
          ],
          "is_new": false,
          "appearance_count": 2,
          "time_info": "[07时27分 ~ 07时50分]"
        },
        {
          "title": "马斯克：特斯拉“有望”在4月份首发下一代Roadster。",
          "url": "https://wallstreetcn.com/livenews/3045887",
          "source": "华尔街见闻-快讯",
          "ranks": [
            2,
            21
          ],
          "is_new": false,
          "appearance_count": 2,
          "time_info": "[07时27分 ~ 07时50分]"
        },
        {
          "title": "财联社1月29日电，特斯拉首席执行官马斯克称，从长远来看，特斯拉每年生产的Cyber Cabs数量将超过其所有其他车型加起来的总和。",
          "url": "https://api3.cls.cn/share/article/2273416?os=web&sv=8.4.6&app=CailianpressWeb",
          "source": "财联社电报",
          "ranks": [
            3,
            18
          ],
          "is_new": false,
          "appearance_count": 2,
          "time_info": "[07时27分 ~ 07时50分]"
        },
        {
          "title": "特斯拉美股盘后快速回吐涨幅，该公司称2026年资本开支将超200亿美元。",
          "url": "https://wallstreetcn.com/livenews/3045885",
          "source": "华尔街见闻-快讯",
          "ranks": [
            3,
            22
          ],
          "is_new": false,
          "appearance_count": 2,
          "time_info": "[07时27分 ~ 07时50分]"
        },
        {
          "title": "财联社1月29日电，特斯拉首席财务官称，特斯拉本季度起将全面转向FSD订阅模式。",
          "url": "https://api3.cls.cn/share/article/2273415?os=web&sv=8.4.6&app=CailianpressWeb",
          "source": "财联社电报",
          "ranks": [
            4,
            19
          ],
          "is_new": false,
          "appearance_count": 2,
          "time_info": "[07时27分 ~ 07时50分]"
        },
        {
          "title": "特斯拉：2026年资本开支将超过200亿美元，那将支持“重大投资（年）”。",
          "url": "https://wallstreetcn.com/livenews/3045884",
          "source": "华尔街见闻-快讯",
          "ranks": [
            4,
            23
          ],
          "is_new": false,
          "appearance_count": 2,
          "time_info": "[07时27分 ~ 07时50分]"
        },
        {
          "title": "特斯拉年收入下滑，为该公司历史上首次。",
          "url": "https://wallstreetcn.com/livenews/3045883",
          "source": "华尔街见闻-快讯",
          "ranks": [
            5,
            24
          ],
          "is_new": false,
          "appearance_count": 2,
          "time_info": "[07时27分 ~ 07时50分]"
        },
        {
          "title": "特斯拉第四季度调整后每股收益高于预期 盘后涨近4%",
          "url": "https://api3.cls.cn/share/article/2273380?os=web&sv=8.4.6&app=CailianpressWeb",
          "source": "财联社电报",
          "ranks": [
            9,
            16
          ],
          "is_new": false,
          "appearance_count": 4,
          "time_info": "[05时55分 ~ 06时27分]"
        },
        {
          "title": "特斯拉将投资20亿美元购买XAI公司的E系列优先股。",
          "url": "https://flash.jin10.com/detail/20260129051210358800",
          "source": "金十数据",
          "ranks": [
            6
          ],
          "is_new": false,
          "appearance_count": 3,
          "time_info": "[05时29分 ~ 05时56分]"
        },
        {
          "title": "特斯拉(TSLA.O)股价在盘后交易中上涨4%，此前第四季度调整后每股收益超出预期。",
          "url": "https://flash.jin10.com/detail/20260129050849422800",
          "source": "金十数据",
          "ranks": [
            7
          ],
          "is_new": false,
          "appearance_count": 3,
          "time_info": "[05时29分 ~ 05时56分]"
        },
        {
          "title": "特斯拉(TSLA.O)：我们计划在今年第一季度发布Optimus的第三代版本。",
          "url": "https://flash.jin10.com/detail/20260129050459592800",
          "source": "金十数据",
          "ranks": [
            15
          ],
          "is_new": false,
          "appearance_count": 3,
          "time_info": "[05时29分 ~ 05时56分]"
        },
        {
          "title": "特斯拉(TSLA.O)Q4毛利率录得20.1%。",
          "url": "https://flash.jin10.com/detail/20260129050407697800",
          "source": "金十数据",
          "ranks": [
            17
          ],
          "is_new": false,
          "appearance_count": 3,
          "time_info": "[05时29分 ~ 05时56分]"
        },
        {
          "title": "特斯拉(TSLA.O)2025年Q4营收249亿美元，市场预期为247.8亿美元，上年同期257.07亿美元。",
          "url": "https://flash.jin10.com/detail/20260129050347553800",
          "source": "金十数据",
          "ranks": [
            18
          ],
          "is_new": false,
          "appearance_count": 3,
          "time_info": "[05时29分 ~ 05时56分]"
        },
        {
          "title": "特斯拉(TSLA.O)美股盘后现涨3%。",
          "url": "https://flash.jin10.com/detail/20260129053426174800",
          "source": "金十数据",
          "ranks": [
            22
          ],
          "is_new": false,
          "appearance_count": 3,
          "time_info": "[06时26分 ~ 06时55分]"
        },
        {
          "title": "摩根士丹利：将特斯拉(TSLA.O)目标股价从425美元下调至415美元。",
          "url": "https://flash.jin10.com/detail/20260129154026023800",
          "source": "金十数据",
          "ranks": [
            7
          ],
          "is_new": false,
          "appearance_count": 2,
          "time_info": "[16时01分 ~ 16时02分]"
        },
        {
          "title": "美股异动｜特斯拉营收下滑 盘后涨超4%",
          "url": "https://www.gelonghui.com/news/5159459",
          "source": "格隆汇",
          "ranks": [
            7
          ],
          "is_new": false,
          "appearance_count": 2,
          "time_info": "[07时27分 ~ 07时50分]"
        },
        {
          "title": "特斯拉：无人驾驶出租车RoboTaxi服务将投放美国更多城市。",
          "url": "https://wallstreetcn.com/livenews/3045882",
          "source": "华尔街见闻-快讯",
          "ranks": [
            6,
            25
          ],
          "is_new": false,
          "appearance_count": 2,
          "time_info": "[07时27分 ~ 07时50分]"
        },
        {
          "title": "特斯拉CEO埃隆·马斯克：不打算在特斯拉之外销售芯片，因为我们需要它们。",
          "url": "https://flash.jin10.com/detail/20260129071338403800",
          "source": "金十数据",
          "ranks": [
            8
          ],
          "is_new": false,
          "appearance_count": 2,
          "time_info": "[07时27分 ~ 07时50分]"
        },
        {
          "title": "特斯拉：将进一步投资清洁交通基础设施。",
          "url": "https://wallstreetcn.com/livenews/3045836",
          "source": "华尔街见闻-快讯",
          "ranks": [
            10,
            19
          ],
          "is_new": false,
          "appearance_count": 2,
          "time_info": "[05时56分 ~ 06时27分]"
        },
        {
          "title": "特斯拉四季度营收249亿美元，分析师预期251.1亿美元。 四季度EPS为0.50美元，分析师预期0.45美元。 四季度毛利润率20.1%，分析师预期17.1%。 四季度运营利润14.1亿美元，分析师预期13.2亿美元。 四季度自由现金流（FCF）14.2亿美元，分析师预期15.9亿美元。",
          "url": "https://wallstreetcn.com/livenews/3045833",
          "source": "华尔街见闻-快讯",
          "ranks": [
            11,
            20
          ],
          "is_new": false,
          "appearance_count": 2,
          "time_info": "[05时56分 ~ 06时27分]"
        },
        {
          "title": "特斯拉CEO埃隆·马斯克：预计Optimus的大规模量产可能要到今年年底才能实现。",
          "url": "https://flash.jin10.com/detail/20260129070735901800",
          "source": "金十数据",
          "ranks": [
            13
          ],
          "is_new": false,
          "appearance_count": 2,
          "time_info": "[07时27分 ~ 07时50分]"
        },
        {
          "title": "特斯拉CEO埃隆·马斯克：公司目前没有裁员计划。",
          "url": "https://flash.jin10.com/detail/20260129070733109800",
          "source": "金十数据",
          "ranks": [
            14
          ],
          "is_new": false,
          "appearance_count": 2,
          "time_info": "[07时27分 ~ 07时50分]"
        },
        {
          "title": "纳斯达克金龙中国指数收涨0.32%，报7892.01点。 热门中概股里，新东方初步收涨4.9%，比亚迪、理想涨超2%，阿里、网易、小米、美团涨超1%，蔚来跌超0.7%，文远知行跌1.9%，拼多多跌3.8%。 ETF中，中概互联网指数ETF（KWEB）收涨0.53%，中国科技指数ETF（CQQQ）收涨0.10%。 XtrackersHarvest中证50（ASHS）收跌0.12%，德银嘉实沪深300指数ETF（ASHR）收跌0.33%。",
          "url": "https://wallstreetcn.com/livenews/3045827",
          "source": "华尔街见闻-快讯",
          "ranks": [
            14,
            23
          ],
          "is_new": false,
          "appearance_count": 2,
          "time_info": "[05时56分 ~ 06时27分]"
        },
        {
          "title": "特斯拉CEO埃隆·马斯克：预计随着时间的推移，将增加弗里蒙特工厂的员工人数。",
          "url": "https://flash.jin10.com/detail/20260129070731400800",
          "source": "金十数据",
          "ranks": [
            15
          ],
          "is_new": false,
          "appearance_count": 2,
          "time_info": "[07时27分 ~ 07时50分]"
        },
        {
          "title": "财联社1月29日电，摩根士丹利将特斯拉目标价从425美元下调至415美元。",
          "url": "https://api3.cls.cn/share/article/2274053?os=web&sv=8.4.6&app=CailianpressWeb",
          "source": "财联社电报",
          "ranks": [
            19
          ],
          "is_new": false,
          "appearance_count": 2,
          "time_info": "[16时01分 ~ 16时02分]"
        },
        {
          "title": "特斯拉CEO埃隆·马斯克：预计将于4月推出下一代Roadster跑车。",
          "url": "https://flash.jin10.com/detail/20260129070055526800",
          "source": "金十数据",
          "ranks": [
            22
          ],
          "is_new": false,
          "appearance_count": 2,
          "time_info": "[07时27分 ~ 07时50分]"
        },
        {
          "title": "特斯拉CEO埃隆·马斯克：从长远来看，特斯拉每年生产的Cyber Cabs数量将超过其所有其他车型加起来的总和。",
          "url": "https://flash.jin10.com/detail/20260129065749945800",
          "source": "金十数据",
          "ranks": [
            26
          ],
          "is_new": false,
          "appearance_count": 2,
          "time_info": "[07时27分 ~ 07时50分]"
        },
        {
          "title": "特斯拉首席财务官：预计2026年的资本支出将超过200亿美元。",
          "url": "https://flash.jin10.com/detail/20260129065110872800",
          "source": "金十数据",
          "ranks": [
            29
          ],
          "is_new": false,
          "appearance_count": 2,
          "time_info": "[07时27分 ~ 07时50分]"
        },
        {
          "title": "财联社1月29日电，特斯拉首席财务官称，随着Optimus的生产和扩张启动，资本支出正投入计算领域，用于训练Optimus。",
          "url": "https://api3.cls.cn/share/article/2273434?os=web&sv=8.4.6&app=CailianpressWeb",
          "source": "财联社电报",
          "ranks": [
            7
          ],
          "is_new": false,
          "appearance_count": 1,
          "time_info": "07时50分"
        },
        {
          "title": "特斯拉CFO：随着Optimus的生产和扩张启动，资本支出正投入计算领域，用于训练Optimus。",
          "url": "https://wallstreetcn.com/livenews/3045901",
          "source": "华尔街见闻-快讯",
          "ranks": [
            7
          ],
          "is_new": false,
          "appearance_count": 1,
          "time_info": "07时50分"
        },
        {
          "title": "财联社1月29日电，特斯拉首席执行官马斯克表示，特斯拉需要建造半导体工厂。",
          "url": "https://api3.cls.cn/share/article/2273431?os=web&sv=8.4.6&app=CailianpressWeb",
          "source": "财联社电报",
          "ranks": [
            10
          ],
          "is_new": false,
          "appearance_count": 1,
          "time_info": "07时50分"
        },
        {
          "title": "马斯克表示，特斯拉需要建立半导体工厂。 特斯拉芯片将“自用”。",
          "url": "https://wallstreetcn.com/livenews/3045898",
          "source": "华尔街见闻-快讯",
          "ranks": [
            10
          ],
          "is_new": false,
          "appearance_count": 1,
          "time_info": "07时50分"
        },
        {
          "title": "财联社1月29日电，特斯拉首席执行官马斯克表示，预计Optimus的大规模量产可能要到今年年底才能实现。",
          "url": "https://api3.cls.cn/share/article/2273428?os=web&sv=8.4.6&app=CailianpressWeb",
          "source": "财联社电报",
          "ranks": [
            12
          ],
          "is_new": false,
          "appearance_count": 1,
          "time_info": "07时50分"
        },
        {
          "title": "马斯克：特斯拉预计将在美国Fremont工厂聘请更多的员工，（那里）还没有任何裁员计划。",
          "url": "https://wallstreetcn.com/livenews/3045893",
          "source": "华尔街见闻-快讯",
          "ranks": [
            15
          ],
          "is_new": false,
          "appearance_count": 1,
          "time_info": "07时50分"
        },
        {
          "title": "提醒：特斯拉电话会开始，马斯克发表开场白讲话。",
          "url": "https://wallstreetcn.com/livenews/3045871",
          "source": "华尔街见闻-快讯",
          "ranks": [
            16
          ],
          "is_new": false,
          "appearance_count": 1,
          "time_info": "07时27分"
        }
      ]
    },
    {
      "keyword_group": "AI Agent AI智能体 AI应用 人工智能",
      "match_count": 23,
      "titles": [
        {
          "title": "特斯拉与XAI框架达成协议，评估人工智能合作。",
          "url": "https://flash.jin10.com/detail/20260129051436140800",
          "source": "金十数据",
          "ranks": [
            4
          ],
          "is_new": false,
          "appearance_count": 3,
          "time_info": "[05时29分 ~ 05时56分]"
        },
        {
          "title": "财联社1月29日电，Meta CEO扎克伯格表示，人工智能眼镜的销量去年增长了三倍多。",
          "url": "https://api3.cls.cn/share/article/2273395?os=web&sv=8.4.6&app=CailianpressWeb",
          "source": "财联社电报",
          "ranks": [
            2,
            10,
            20
          ],
          "is_new": false,
          "appearance_count": 4,
          "time_info": "[06时26分 ~ 07时27分]"
        },
        {
          "title": "财联社1月29日电，三星电子称，预计第一季人工智能对芯片的需求强劲。",
          "url": "https://api3.cls.cn/share/article/2273414?os=web&sv=8.4.6&app=CailianpressWeb",
          "source": "财联社电报",
          "ranks": [
            5,
            20
          ],
          "is_new": false,
          "appearance_count": 2,
          "time_info": "[07时27分 ~ 07时50分]"
        },
        {
          "title": "Meta Platforms CEO扎克伯格：人工智能眼镜销量去年增长逾两倍。",
          "url": "https://flash.jin10.com/detail/20260129055602518800",
          "source": "金十数据",
          "ranks": [
            7
          ],
          "is_new": false,
          "appearance_count": 3,
          "time_info": "[06时26分 ~ 06时55分]"
        },
        {
          "title": "Meta Platforms(META.O)计划招聘人员以支持优先领域，尤其是人工智能。",
          "url": "https://flash.jin10.com/detail/20260129050300476800",
          "source": "金十数据",
          "ranks": [
            19
          ],
          "is_new": false,
          "appearance_count": 3,
          "time_info": "[05时29分 ~ 05时56分]"
        },
        {
          "title": "财联社1月29日电，美联储主席鲍威尔表示，短期内可能会看到因人工智能赋能而出现的岗位被取代，但其总体影响尚不清楚。",
          "url": "https://api3.cls.cn/share/article/2273365?os=web&sv=8.4.6&app=CailianpressWeb",
          "source": "财联社电报",
          "ranks": [
            6,
            12
          ],
          "is_new": false,
          "appearance_count": 2,
          "time_info": "[04时31分 ~ 05时29分]"
        },
        {
          "title": "鲍威尔：短期内可能会看到人工智能（AI）消除就业岗位/AI导致岗位被淘汰。",
          "url": "https://wallstreetcn.com/livenews/3045805",
          "source": "华尔街见闻-快讯",
          "ranks": [
            9,
            23
          ],
          "is_new": false,
          "appearance_count": 2,
          "time_info": "[04时31分 ~ 05时29分]"
        },
        {
          "title": "港股异动丨AI应用概念集体走强，迈富时涨超6%",
          "url": "https://www.gelonghui.com/news/5159530",
          "source": "格隆汇",
          "ranks": [
            10
          ],
          "is_new": false,
          "appearance_count": 2,
          "time_info": "[12时11分 ~ 12时12分]"
        },
        {
          "title": "Meta四季度营收598.9亿美元，分析师预期584.2亿美元。 四季度运营利润247.5亿美元，同比增长5.9%。 预计2026年资本开支1150亿-1350亿美元，分析师预期1106.2亿美元。 预计2026年总体开支1620亿 预计一季度营收535亿-565亿美元，分析师预期512.7亿美元。 公司将在优先领域招聘，尤其是人工智能（AI）方面。",
          "url": "https://wallstreetcn.com/livenews/3045830",
          "source": "华尔街见闻-快讯",
          "ranks": [
            12,
            21
          ],
          "is_new": false,
          "appearance_count": 2,
          "time_info": "[05时56分 ~ 06时27分]"
        },
        {
          "title": "AI应用大爆发，传媒ETF华夏(516190)跃升6%，百亿规模游戏ETF(159869)连续5日净流入",
          "url": "https://www.gelonghui.com/news/5159526",
          "source": "格隆汇",
          "ranks": [
            14
          ],
          "is_new": false,
          "appearance_count": 2,
          "time_info": "[12时11分 ~ 12时12分]"
        },
        {
          "title": "英国寻求利用人工智能提升生产力 以弥补失业损失",
          "url": "https://flash.jin10.com/detail/20260129014249845800",
          "source": "金十数据",
          "ranks": [
            25
          ],
          "is_new": false,
          "appearance_count": 2,
          "time_info": "[02时37分 ~ 02时38分]"
        },
        {
          "title": "特斯拉首席财务官：公司在人工智能相关项目和新产品的支出仍处于较高水平。",
          "url": "https://flash.jin10.com/detail/20260129065025610800",
          "source": "金十数据",
          "ranks": [
            30
          ],
          "is_new": false,
          "appearance_count": 2,
          "time_info": "[07时27分 ~ 07时50分]"
        },
        {
          "title": "港股ai应用走强 MINIMAX涨超14%",
          "url": "https://api3.cls.cn/share/article/2273597?os=web&sv=8.4.6&app=CailianpressWeb",
          "source": "财联社电报",
          "ranks": [
            7
          ],
          "is_new": false,
          "appearance_count": 1,
          "time_info": "09时59分"
        },
        {
          "title": "英伟达CEO黄仁勋：内存对人工智能的未来至关重要。",
          "url": "https://flash.jin10.com/detail/20260129133336783800",
          "source": "金十数据",
          "ranks": [
            10
          ],
          "is_new": false,
          "appearance_count": 1,
          "time_info": "14时07分"
        },
        {
          "title": "1月29日午间收评：创业板指冲高回落微跌，AI应用端集体爆发",
          "url": "https://wallstreetcn.com/livenews/3046069",
          "source": "华尔街见闻-快讯",
          "ranks": [
            11
          ],
          "is_new": false,
          "appearance_count": 1,
          "time_info": "12时12分"
        },
        {
          "title": "AI应用端局部异动 天地在线、华媒控股双双涨停",
          "url": "https://api3.cls.cn/share/article/2273590?os=web&sv=8.4.6&app=CailianpressWeb",
          "source": "财联社电报",
          "ranks": [
            14
          ],
          "is_new": false,
          "appearance_count": 1,
          "time_info": "09时59分"
        },
        {
          "title": "财联社1月29日电，诺基亚首席执行官称，仍在对业务组合进行转型，以更聚焦于人工智能和云领域。",
          "url": "https://api3.cls.cn/share/article/2273965?os=web&sv=8.4.6&app=CailianpressWeb",
          "source": "财联社电报",
          "ranks": [
            14
          ],
          "is_new": false,
          "appearance_count": 1,
          "time_info": "15时14分"
        },
        {
          "title": "中国已批准进口首批英伟达H200人工智能芯片？外交部回应",
          "url": "https://wallstreetcn.com/livenews/3046225",
          "source": "华尔街见闻-快讯",
          "ranks": [
            14
          ],
          "is_new": true,
          "appearance_count": 1,
          "time_info": "16时02分"
        },
        {
          "title": "三星电子：将加大人工智能相关芯片的比重。",
          "url": "https://flash.jin10.com/detail/20260129092640386800",
          "source": "金十数据",
          "ranks": [
            16
          ],
          "is_new": false,
          "appearance_count": 1,
          "time_info": "09时59分"
        },
        {
          "title": "【机构调研】这家公司AI智能体平台聚焦政企数字化场景，相关应用已在项目订单中产生收入",
          "url": "https://api3.cls.cn/share/article/2273814?os=web&sv=8.4.6&app=CailianpressWeb",
          "source": "财联社电报",
          "ranks": [
            17
          ],
          "is_new": false,
          "appearance_count": 1,
          "time_info": "13时29分"
        },
        {
          "title": "美联储主席鲍威尔：最近大学毕业生的低就业率似乎与人工智能存在某种关联。",
          "url": "https://flash.jin10.com/detail/20260129040422836800",
          "source": "金十数据",
          "ranks": [
            21
          ],
          "is_new": false,
          "appearance_count": 1,
          "time_info": "04时31分"
        },
        {
          "title": "美联储主席鲍威尔：短期内，我们可能会看到一些工作岗位因人工智能技术的应用而被取代，但尚不清楚整体影响。",
          "url": "https://flash.jin10.com/detail/20260129040407090800",
          "source": "金十数据",
          "ranks": [
            22
          ],
          "is_new": false,
          "appearance_count": 1,
          "time_info": "04时31分"
        },
        {
          "title": "美联储主席鲍威尔：（经济）受益于人工智能支出。",
          "url": "https://flash.jin10.com/detail/20260129040018734800",
          "source": "金十数据",
          "ranks": [
            28
          ],
          "is_new": false,
          "appearance_count": 1,
          "time_info": "04时31分"
        }
      ]
    },
    {
      "keyword_group": "台积电 英伟达",
      "match_count": 20,
      "titles": [
        {
          "title": "评论：美议员称英伟达助深度求索强化的AI模型 被中国军方使用",
          "url": "https://www.zaochenbao.com/news/opinion/202601/2963506.html",
          "source": "早报",
          "ranks": [
            4,
            8,
            11,
            14,
            20
          ],
          "is_new": false,
          "appearance_count": 7,
          "time_info": "[12时11分 ~ 16时02分]"
        },
        {
          "title": "黄仁勋称英伟达H200中国许可事宜正在最终敲定中",
          "url": "https://www.zaochenbao.com/news/china/202601/2963526.html",
          "source": "早报",
          "ranks": [
            3
          ],
          "is_new": false,
          "appearance_count": 2,
          "time_info": "[16时01分 ~ 16时02分]"
        },
        {
          "title": "英伟达(NVDA.O)：美国国会必须重新授权国家量子倡议。",
          "url": "https://flash.jin10.com/detail/20260129022459391800",
          "source": "金十数据",
          "ranks": [
            3
          ],
          "is_new": false,
          "appearance_count": 2,
          "time_info": "[02时37分 ~ 02时38分]"
        },
        {
          "title": "英伟达CEO黄仁勋：当然会与台积电首席执行官会面。",
          "url": "https://flash.jin10.com/detail/20260129133946583800",
          "source": "金十数据",
          "ranks": [
            2
          ],
          "is_new": false,
          "appearance_count": 1,
          "time_info": "14时07分"
        },
        {
          "title": "英伟达CEO黄仁勋：在台湾期间将拜访我们的合作伙伴。",
          "url": "https://flash.jin10.com/detail/20260129133927733800",
          "source": "金十数据",
          "ranks": [
            3
          ],
          "is_new": false,
          "appearance_count": 1,
          "time_info": "14时07分"
        },
        {
          "title": "标普500指数初步大致收平，能源板块涨0.8%，科技板块涨0.6%，保健板块跌0.7%，房地产板块跌0.8%。 纳斯达克100指数初步收涨0.4%，成分股中，希捷科技初步收涨超19%，英特尔涨10.9%，西部数据涨10%，德州仪器、微芯科技、MPWR、美光科技、恩智浦至少涨超4.6%，拼多多则跌超3%，Arm控股跌4.4%，Palantir跌4.8%，AXON跌9.5%。 联合健康收盘初步反弹4%，英伟达、强生、SHW涨超1%，领跑道指成分股，波音则跌0.9%，家得宝跌1.3%，霍尼韦尔跌1.8%，安进跌2.5%。",
          "url": "https://wallstreetcn.com/livenews/3045825",
          "source": "华尔街见闻-快讯",
          "ranks": [
            4
          ],
          "is_new": false,
          "appearance_count": 1,
          "time_info": "05时29分"
        },
        {
          "title": "美国总统特朗普称赞英伟达为“特朗普账户”捐款。",
          "url": "https://flash.jin10.com/detail/20260129004308229800",
          "source": "金十数据",
          "ranks": [
            5
          ],
          "is_new": false,
          "appearance_count": 1,
          "time_info": "01时33分"
        },
        {
          "title": "美议员称英伟达助深度求索强化的AI模型被中国军方使用",
          "url": "https://www.zaochenbao.com/news/china/202601/2963504.html",
          "source": "早报",
          "ranks": [
            6,
            10,
            13,
            16
          ],
          "is_new": false,
          "appearance_count": 5,
          "time_info": "[12时11分 ~ 15时14分]"
        },
        {
          "title": "据路透社报道：英伟达CEO黄仁勋抵达台北。",
          "url": "https://flash.jin10.com/detail/20260129132152692800",
          "source": "金十数据",
          "ranks": [
            1,
            18
          ],
          "is_new": false,
          "appearance_count": 2,
          "time_info": "[13时29分 ~ 14时07分]"
        },
        {
          "title": "美国总统特朗普在“特朗普账户”活动上赞赏英伟达的捐款。",
          "url": "https://wallstreetcn.com/livenews/3045719",
          "source": "华尔街见闻-快讯",
          "ranks": [
            5,
            20
          ],
          "is_new": false,
          "appearance_count": 2,
          "time_info": "[01时33分 ~ 02时38分]"
        },
        {
          "title": "英伟达CEO黄仁勋：台积电将必须大幅增加产能。",
          "url": "https://flash.jin10.com/detail/20260129133637086800",
          "source": "金十数据",
          "ranks": [
            6
          ],
          "is_new": false,
          "appearance_count": 1,
          "time_info": "14时07分"
        },
        {
          "title": "英伟达CEO黄仁勋：今年我们将实现相当可观的增长。",
          "url": "https://flash.jin10.com/detail/20260129133406913800",
          "source": "金十数据",
          "ranks": [
            9
          ],
          "is_new": false,
          "appearance_count": 1,
          "time_info": "14时07分"
        },
        {
          "title": "英伟达CEO黄仁勋：台积电是全球最优秀的（芯片制造商）。",
          "url": "https://flash.jin10.com/detail/20260129133055268800",
          "source": "金十数据",
          "ranks": [
            13
          ],
          "is_new": false,
          "appearance_count": 1,
          "time_info": "14时07分"
        },
        {
          "title": "英伟达CEO黄仁勋：我们与英特尔有着强大的合作关系。",
          "url": "https://flash.jin10.com/detail/20260129133011047800",
          "source": "金十数据",
          "ranks": [
            14
          ],
          "is_new": false,
          "appearance_count": 1,
          "time_info": "14时07分"
        },
        {
          "title": "英伟达CEO黄仁勋：需求非常强劲。",
          "url": "https://flash.jin10.com/detail/20260129132849676800",
          "source": "金十数据",
          "ranks": [
            15
          ],
          "is_new": false,
          "appearance_count": 1,
          "time_info": "14时07分"
        },
        {
          "title": "黄仁勋：英伟达今年将实现大幅增长。",
          "url": "https://wallstreetcn.com/livenews/3046137",
          "source": "华尔街见闻-快讯",
          "ranks": [
            15
          ],
          "is_new": false,
          "appearance_count": 1,
          "time_info": "14时07分"
        },
        {
          "title": "英伟达CEO黄仁勋：对台积电的执行情况非常满意。",
          "url": "https://flash.jin10.com/detail/20260129132814034800",
          "source": "金十数据",
          "ranks": [
            16
          ],
          "is_new": false,
          "appearance_count": 1,
          "time_info": "14时07分"
        },
        {
          "title": "英伟达CEO黄仁勋：对Rubin的需求令人难以置信的强劲。能源对美国、台湾和欧洲来说是一个巨大挑战。正与英特尔合作开发定制x86处理器。",
          "url": "https://wallstreetcn.com/livenews/3046136",
          "source": "华尔街见闻-快讯",
          "ranks": [
            16
          ],
          "is_new": false,
          "appearance_count": 1,
          "time_info": "14时07分"
        },
        {
          "title": "英伟达CEO黄仁勋：已访问中国的一些客户与合作伙伴。",
          "url": "https://flash.jin10.com/detail/20260129132652135800",
          "source": "金十数据",
          "ranks": [
            17
          ],
          "is_new": false,
          "appearance_count": 1,
          "time_info": "14时07分"
        },
        {
          "title": "财联社1月29日电，英伟达CEO黄仁勋表示，台积电在未来十年需要大幅增加产能。",
          "url": "https://api3.cls.cn/share/article/2273858?os=web&sv=8.4.6&app=CailianpressWeb",
          "source": "财联社电报",
          "ranks": [
            18
          ],
          "is_new": false,
          "appearance_count": 1,
          "time_info": "14时07分"
        }
      ]
    },
    {
      "keyword_group": "机器人 行星减速器 谐波减速器 力矩传感器 柔性机械臂",
      "match_count": 16,
      "titles": [
        {
          "title": "宇树等机器人企业扎堆上春晚，谁是去年全球出货量第一？",
          "url": "https://m.thepaper.cn/newsDetail_forward_32475040",
          "source": "澎湃新闻",
          "ranks": [
            12,
            13,
            14,
            16,
            17
          ],
          "is_new": false,
          "appearance_count": 15,
          "time_info": "[00时37分 ~ 07时50分]"
        },
        {
          "title": "特斯拉Q4盈利高于预期，开始局部真正无人驾驶，投资xAI 20亿，Cybecab和机器人待量产，盘后跳涨丨财报见闻",
          "url": "https://wallstreetcn.com/articles/3764408",
          "source": "华尔街见闻",
          "ranks": [
            10,
            9,
            8
          ],
          "is_new": false,
          "appearance_count": 7,
          "time_info": "[12时11分 ~ 16时02分]"
        },
        {
          "title": "通光线缆：公司柔性电缆产品尚未应用于人形机器人",
          "url": "https://www.gelonghui.com/news/5159558",
          "source": "格隆汇",
          "ranks": [
            4,
            10
          ],
          "is_new": false,
          "appearance_count": 2,
          "time_info": "[13时29分 ~ 14时07分]"
        },
        {
          "title": "特斯拉：人形机器人Optimus第一代产品线正在铺设中",
          "url": "https://api3.cls.cn/share/article/2273381?os=web&sv=8.4.6&app=CailianpressWeb",
          "source": "财联社电报",
          "ranks": [
            8,
            15
          ],
          "is_new": false,
          "appearance_count": 4,
          "time_info": "[05时55分 ~ 06时27分]"
        },
        {
          "title": "特斯拉(TSLA.O)：将进一步投资自主机器人基础设施。",
          "url": "https://flash.jin10.com/detail/20260129050817558800",
          "source": "金十数据",
          "ranks": [
            9
          ],
          "is_new": false,
          "appearance_count": 3,
          "time_info": "[05时29分 ~ 05时56分]"
        },
        {
          "title": "特斯拉：CyberCab、Semi、Megapack3都处于2026年规划的正轨之上。 将在多个产品铺开六条新的产品线。 公司将投资20亿美元，购买xAI的系列E优先股；特斯拉与xAI就此达成框架协议。 Cybercab和特斯拉Semi有望在2026年量产，Megapack3也有望在今年量产。 人形机器人Optimus第一代产品线正在铺设中。",
          "url": "https://wallstreetcn.com/livenews/3045838",
          "source": "华尔街见闻-快讯",
          "ranks": [
            8,
            17,
            29
          ],
          "is_new": false,
          "appearance_count": 3,
          "time_info": "[05时56分 ~ 06时55分]"
        },
        {
          "title": "埃夫特机器人：对公司部分工业机器人整机产品售价进行优化调整 调价幅度区间为5%—12%",
          "url": "https://api3.cls.cn/share/article/2273773?os=web&sv=8.4.6&app=CailianpressWeb",
          "source": "财联社电报",
          "ranks": [
            9
          ],
          "is_new": false,
          "appearance_count": 2,
          "time_info": "[12时11分 ~ 12时12分]"
        },
        {
          "title": "阿里巴巴(09988.HK)：菜鸟无人车业务与九识智能达成战略合作伙伴关系，菜鸟将成为九识智能的股东，将合作助力九识智能打造机器人货车。",
          "url": "https://flash.jin10.com/detail/20260129153951436800",
          "source": "金十数据",
          "ranks": [
            9
          ],
          "is_new": false,
          "appearance_count": 2,
          "time_info": "[16时01分 ~ 16时02分]"
        },
        {
          "title": "马斯克要发力机器人了？2026年训练、制造两手抓 第三代Optimus即将推出",
          "url": "https://www.cls.cn/detail/2273549",
          "source": "财联社热门",
          "ranks": [
            12
          ],
          "is_new": false,
          "appearance_count": 2,
          "time_info": "[16时01分 ~ 16时02分]"
        },
        {
          "title": "民政部：广泛应用人形机器人、脑机接口、人工智能等前沿技术 研制高性能智能养老服务机器人",
          "url": "https://www.cls.cn/detail/2273653",
          "source": "财联社热门",
          "ranks": [
            13
          ],
          "is_new": false,
          "appearance_count": 2,
          "time_info": "[16时01分 ~ 16时02分]"
        },
        {
          "title": "特斯拉首席财务官：特斯拉可能在几个月内发布Optimus机器人。",
          "url": "https://flash.jin10.com/detail/20260129065415139800",
          "source": "金十数据",
          "ranks": [
            28
          ],
          "is_new": false,
          "appearance_count": 2,
          "time_info": "[07时27分 ~ 07时50分]"
        },
        {
          "title": "银河通用发布首款工业级重载机器人，Galbot G1年出货破1200台",
          "url": "https://wallstreetcn.com/livenews/3046149",
          "source": "华尔街见闻-快讯",
          "ranks": [
            6
          ],
          "is_new": false,
          "appearance_count": 1,
          "time_info": "14时07分"
        },
        {
          "title": "财联社1月29日电，特斯拉首席执行官马斯克称，2026年资本支出将“非常大”；预计下季度将开始逐步停止Model S和Model X的生产，弗里蒙特工厂转型为生产Optimus人形机器人。",
          "url": "https://api3.cls.cn/share/article/2273410?os=web&sv=8.4.6&app=CailianpressWeb",
          "source": "财联社电报",
          "ranks": [
            8
          ],
          "is_new": false,
          "appearance_count": 1,
          "time_info": "07时27分"
        },
        {
          "title": "特斯拉将停产Model S和X，将生产线转至制造人形机器人Optimus。",
          "url": "https://wallstreetcn.com/livenews/3045875",
          "source": "华尔街见闻-快讯",
          "ranks": [
            12
          ],
          "is_new": false,
          "appearance_count": 1,
          "time_info": "07时27分"
        },
        {
          "title": "马斯克：人形机器人Optimus仍然处于早期阶段，它正在工厂做一些基础任务，还没有大规模应用。",
          "url": "https://wallstreetcn.com/livenews/3045892",
          "source": "华尔街见闻-快讯",
          "ranks": [
            16
          ],
          "is_new": false,
          "appearance_count": 1,
          "time_info": "07时50分"
        },
        {
          "title": "据华尔街日报：阿里巴巴(09988.HK)将与九识智能共同运营价值20亿美元的机器人自动化业务。",
          "url": "https://flash.jin10.com/detail/20260129143957150800",
          "source": "金十数据",
          "ranks": [
            26
          ],
          "is_new": false,
          "appearance_count": 1,
          "time_info": "15时14分"
        }
      ]
    },
    {
      "keyword_group": "美债 美股 美元",
      "match_count": 11,
      "titles": [
        {
          "title": "美股三大指数收盘涨跌不一，纳指收涨0.17%",
          "url": "https://www.gelonghui.com/news/5159458",
          "source": "格隆汇",
          "ranks": [
            1,
            8
          ],
          "is_new": false,
          "appearance_count": 5,
          "time_info": "[06时26分 ~ 07时50分]"
        },
        {
          "title": "美股七巨头收盘播报｜周三（1月28日），美国科技股七巨头（Magnificent 7）指数涨0.22%，报209.62点，整体呈现出V形反转行情，美联储发布决议声明后持续走高。 “超大”市值科技股指数涨0.04%，报398.55点，跳空高开之后持续回吐涨幅并多次转跌。",
          "url": "https://wallstreetcn.com/livenews/3045853",
          "source": "华尔街见闻-快讯",
          "ranks": [
            4,
            16
          ],
          "is_new": false,
          "appearance_count": 2,
          "time_info": "[06时27分 ~ 06时55分]"
        },
        {
          "title": "（美股）费城金银指数收涨2.38%，报451.13点。 （全球时段）纽约证交所ARCA金矿开采商指数涨3.13%，报3196.53点。 （美股）原材料指数收跌0.29%，金属与矿业指数收跌0.05%。",
          "url": "https://wallstreetcn.com/livenews/3045852",
          "source": "华尔街见闻-快讯",
          "ranks": [
            5,
            17
          ],
          "is_new": false,
          "appearance_count": 2,
          "time_info": "[06时27分 ~ 06时55分]"
        },
        {
          "title": "周三（1月28日）美股尾盘，彭博电动汽车价格回报指数涨0.63%，报3711.30点，亚太时段出现V形反转行情，日内大部分时候高位震荡。 成分股Olectra Greentech涨超10%，EVgo涨8.7%，港股理想汽车收涨4.9%、蔚来集团收涨3.98%表现第四，美国雅宝目前跌5.1%表现倒数第二，Solid Power跌7.6%。",
          "url": "https://wallstreetcn.com/livenews/3045820",
          "source": "华尔街见闻-快讯",
          "ranks": [
            9,
            20,
            29
          ],
          "is_new": false,
          "appearance_count": 3,
          "time_info": "[05时29分 ~ 06时27分]"
        },
        {
          "title": "美股收盘：三大股指涨跌不一 英特尔涨11%",
          "url": "https://flash.jin10.com/detail/20260129050049767800",
          "source": "金十数据",
          "ranks": [
            25
          ],
          "is_new": false,
          "appearance_count": 3,
          "time_info": "[05时29分 ~ 05时56分]"
        },
        {
          "title": "美元指数涨0.89%，报96.63点。 美元兑日元涨1.12%，美元兑瑞郎涨1.34%。 欧元兑美元跌0.99%，英镑兑美元跌0.55%；澳元跌0.36%，纽元跌0.38%，加元跌0.14%。",
          "url": "https://wallstreetcn.com/livenews/3045755",
          "source": "华尔街见闻-快讯",
          "ranks": [
            6,
            16
          ],
          "is_new": false,
          "appearance_count": 2,
          "time_info": "[03时28分 ~ 03时53分]"
        },
        {
          "title": "美国10年期国债收益率涨1.4个基点，报4.2571%；两年期美债收益率涨1.24个基点，持稳于日高3.5875%附近。 10年期TIPS收益率涨1.47个基点，持稳于日高1.9078%附近，两年期TIPS收益率跌1.50个基点，报0.8312%。 2/10年期美债收益率利差涨0.162个基点，报+66.968个基点。",
          "url": "https://wallstreetcn.com/livenews/3045754",
          "source": "华尔街见闻-快讯",
          "ranks": [
            7,
            17
          ],
          "is_new": false,
          "appearance_count": 2,
          "time_info": "[03时28分 ~ 03时53分]"
        },
        {
          "title": "LME期铜收涨80美元，报13086美元/吨。 LME期铝收涨50美元，报3257美元/吨。 LME期锌收涨13美元，报3364美元/吨。 LME期铅收跌3美元，报2017美元/吨。 LME期镍收涨101美元，报18270美元/吨。 LME期锡收涨1075美元，报55953美元/吨。 LME期钴收平，报56290美元/吨。",
          "url": "https://wallstreetcn.com/livenews/3045731",
          "source": "华尔街见闻-快讯",
          "ranks": [
            9,
            27
          ],
          "is_new": false,
          "appearance_count": 2,
          "time_info": "[02时38分 ~ 03时28分]"
        },
        {
          "title": "周四亚太盘初，纳斯达克100股指期货涨0.5%。 目前（美股盘后），科技股IBM涨8.4%，（电话会已经结束的）Meta涨8.3%，Pinterest涨3%，美光涨2.8%，谷歌A涨2.3%，AMD、（电话会仍在继续的）特斯拉涨超1%，（电话会仍在继续的）微软跌5.2%。",
          "url": "https://wallstreetcn.com/livenews/3045888",
          "source": "华尔街见闻-快讯",
          "ranks": [
            20
          ],
          "is_new": false,
          "appearance_count": 1,
          "time_info": "07时50分"
        },
        {
          "title": "现货钯金逆转跌势，日内涨幅扩大至2%，现报2090.56美元/盎司；此前一度跌3%。",
          "url": "https://flash.jin10.com/detail/20260129124851025800",
          "source": "金十数据",
          "ranks": [
            26
          ],
          "is_new": false,
          "appearance_count": 1,
          "time_info": "13时29分"
        },
        {
          "title": "美股涨幅收窄，道指转跌，标普500指数持平，纳斯达克指数涨0.2%。",
          "url": "https://flash.jin10.com/detail/20260128235421935800",
          "source": "金十数据",
          "ranks": [
            29
          ],
          "is_new": false,
          "appearance_count": 1,
          "time_info": "00时37分"
        }
      ]
    },
    {
      "keyword_group": "商业航天 卫星 火箭发动机 激光通信",
      "match_count": 8,
      "titles": [
        {
          "title": "明确“五个一流”新目标 我国商业航天迎“关键十年”",
          "url": "https://www.cls.cn/detail/2273685",
          "source": "财联社热门",
          "ranks": [
            10,
            5,
            4,
            2,
            1
          ],
          "is_new": false,
          "appearance_count": 7,
          "time_info": "[12时11分 ~ 16时02分]"
        },
        {
          "title": "我国商业航天明确“五个一流”新目标！资金盘中抢筹航空航天ETF天弘（159241），已连续5日“吸金”",
          "url": "https://www.gelonghui.com/news/5159559",
          "source": "格隆汇",
          "ranks": [
            3,
            9
          ],
          "is_new": false,
          "appearance_count": 2,
          "time_info": "[13时29分 ~ 14时07分]"
        },
        {
          "title": "星宸科技(301536.SZ)：公司目前暂不涉及卫星业务",
          "url": "https://www.gelonghui.com/news/5159553",
          "source": "格隆汇",
          "ranks": [
            9,
            15
          ],
          "is_new": false,
          "appearance_count": 2,
          "time_info": "[13时29分 ~ 14时07分]"
        },
        {
          "title": "太空电子器件迎革命性突破 卫星将更轻、更耐用、更省电",
          "url": "https://api3.cls.cn/share/article/2273753?os=web&sv=8.4.6&app=CailianpressWeb",
          "source": "财联社电报",
          "ranks": [
            15
          ],
          "is_new": false,
          "appearance_count": 2,
          "time_info": "[12时11分 ~ 12时12分]"
        },
        {
          "title": "【风口研报·公司】铜、钴、钼保有储量国内领先，分析师强call这家“隐形”资源大佬矿产亟待重估，且还承建了海南商业航天发射场",
          "url": "https://api3.cls.cn/share/article/2273729?os=web&sv=8.4.6&app=CailianpressWeb",
          "source": "财联社电报",
          "ranks": [
            13
          ],
          "is_new": false,
          "appearance_count": 1,
          "time_info": "13时29分"
        },
        {
          "title": "国家航天局：持续优化商业航天发展政策环境",
          "url": "https://api3.cls.cn/share/article/2273825?os=web&sv=8.4.6&app=CailianpressWeb",
          "source": "财联社电报",
          "ranks": [
            14
          ],
          "is_new": false,
          "appearance_count": 1,
          "time_info": "13时29分"
        },
        {
          "title": "中国商业航天火箭卫星将加速升级 开发更多应用场景",
          "url": "https://wallstreetcn.com/livenews/3046049",
          "source": "华尔街见闻-快讯",
          "ranks": [
            23
          ],
          "is_new": false,
          "appearance_count": 1,
          "time_info": "12时12分"
        },
        {
          "title": "央视新闻：明确“五个一流”新目标 我国商业航天迎“关键十年”",
          "url": "https://wallstreetcn.com/livenews/3046038",
          "source": "华尔街见闻-快讯",
          "ranks": [
            30
          ],
          "is_new": false,
          "appearance_count": 1,
          "time_info": "12时12分"
        }
      ]
    },
    {
      "keyword_group": "金价 黄金",
      "match_count": 7,
      "titles": [
        {
          "title": "美联储决议前，强劲财报提振科技股，标普500突破7000点创新高，阿斯麦转跌，美元止跌，黄金5300，银、铜、铝集体上涨",
          "url": "https://wallstreetcn.com/articles/3764338",
          "source": "华尔街见闻",
          "ranks": [
            2,
            1
          ],
          "is_new": false,
          "appearance_count": 13,
          "time_info": "[00时37分 ~ 06时55分]"
        },
        {
          "title": "【每日收评】三大指数震荡分化涨跌不一，全市场超3600股飘绿，黄金、油气等周期股持续爆发",
          "url": "https://www.cls.cn/detail/2272713",
          "source": "财联社热门",
          "ranks": [
            10,
            9,
            8
          ],
          "is_new": false,
          "appearance_count": 15,
          "time_info": "[00时37分 ~ 07时50分]"
        },
        {
          "title": "上海黄金交易所黄金T+D 1月28日（周三）晚盘收盘上涨2.39%报1190.75元/克；<br/>上海黄金交易所白银T+D 1月28日（周三）晚盘收盘下跌0.13%报28981.0元/千克。",
          "url": "https://flash.jin10.com/detail/20260129023052248800",
          "source": "金十数据",
          "ranks": [
            2
          ],
          "is_new": false,
          "appearance_count": 2,
          "time_info": "[02时37分 ~ 02时38分]"
        },
        {
          "title": "A股午评：半日成交额超2万亿！三大指数涨跌互现，黄金、地产股表现强势",
          "url": "https://www.gelonghui.com/news/5159535",
          "source": "格隆汇",
          "ranks": [
            5
          ],
          "is_new": false,
          "appearance_count": 2,
          "time_info": "[12时11分 ~ 12时12分]"
        },
        {
          "title": "美联储决议无新意，美股涨跌互现，希捷飙升19%领涨存储股，黄金突破5400美元",
          "url": "https://wallstreetcn.com/articles/3764338",
          "source": "华尔街见闻",
          "ranks": [
            1
          ],
          "is_new": false,
          "appearance_count": 1,
          "time_info": "07时27分"
        },
        {
          "title": "现货黄金涨1.80%，暂报5274.50美元；COMEX黄金期货涨3.71%。 现货白银跌0.65%，纽约期银涨5.15%。 COMEX铜期货涨0.96%。 WTI原油期货涨1.17%，布油涨1.01%。",
          "url": "https://wallstreetcn.com/livenews/3045756",
          "source": "华尔街见闻-快讯",
          "ranks": [
            5,
            15
          ],
          "is_new": false,
          "appearance_count": 2,
          "time_info": "[03时28分 ~ 03时53分]"
        },
        {
          "title": "美国10年期国债收益率短线波动超1个基点，刷新日高至4.26%上方，两年期美债收益率短线波动超1.5个基点，刷新日高至3.59%上方。标普和道指跌幅略微扩大至超过0.1%，现货黄金持稳于5270美元一线，涨幅超过1.7%。 MSCI新兴市场汇率指数、股票指数双双持稳。",
          "url": "https://wallstreetcn.com/livenews/3045763",
          "source": "华尔街见闻-快讯",
          "ranks": [
            9
          ],
          "is_new": false,
          "appearance_count": 1,
          "time_info": "03时53分"
        }
      ]
    },
    {
      "keyword_group": "算力 智算中心 AI芯片 GPU NPU ASIC SOC",
      "match_count": 5,
      "titles": [
        {
          "title": "亿田智能(300911.SZ)：目前庆阳智算中心可以提供算力服务",
          "url": "https://www.gelonghui.com/news/5160111",
          "source": "格隆汇",
          "ranks": [
            1
          ],
          "is_new": false,
          "appearance_count": 1,
          "time_info": "15时14分"
        },
        {
          "title": "特斯拉(TSLA.O)：我们计划在2026年上半年将位于德克萨斯州的本地计算规模（以H100等效算力计）扩大一倍以上。",
          "url": "https://flash.jin10.com/detail/20260129050532661800",
          "source": "金十数据",
          "ranks": [
            14
          ],
          "is_new": false,
          "appearance_count": 3,
          "time_info": "[05时29分 ~ 05时56分]"
        },
        {
          "title": "阿里平头哥新款AI芯片正式亮相！",
          "url": "https://www.cls.cn/detail/2273750",
          "source": "财联社热门",
          "ranks": [
            10
          ],
          "is_new": false,
          "appearance_count": 2,
          "time_info": "[16时01分 ~ 16时02分]"
        },
        {
          "title": "蓝箭电子：公司先进封装技术尚未直接应用于AI芯片、高性能计算芯片的封装",
          "url": "https://api3.cls.cn/share/article/2273762?os=web&sv=8.4.6&app=CailianpressWeb",
          "source": "财联社电报",
          "ranks": [
            13
          ],
          "is_new": false,
          "appearance_count": 2,
          "time_info": "[12时11分 ~ 12时12分]"
        },
        {
          "title": "算力硬件股震荡走强 可川科技10天5板续创历史新高",
          "url": "https://api3.cls.cn/share/article/2273599?os=web&sv=8.4.6&app=CailianpressWeb",
          "source": "财联社电报",
          "ranks": [
            8
          ],
          "is_new": false,
          "appearance_count": 1,
          "time_info": "09时59分"
        }
      ]
    },
    {
      "keyword_group": "deepseek 梁文锋 google Gemini chatgpt OpenAI",
      "match_count": 5,
      "titles": [
        {
          "title": "一位前OpenAI高级研究员创办了一家新的人工智能初创公司，目标是筹集高达10亿美元的资金。",
          "url": "https://flash.jin10.com/detail/20260129071859575800",
          "source": "金十数据",
          "ranks": [
            4
          ],
          "is_new": false,
          "appearance_count": 2,
          "time_info": "[07时27分 ~ 07时50分]"
        },
        {
          "title": "美媒：英伟达微软亚马逊洽谈投资OpenAI",
          "url": "https://www.zaochenbao.com/news/politics/202601/2963518.html",
          "source": "早报",
          "ranks": [
            2,
            11
          ],
          "is_new": false,
          "appearance_count": 3,
          "time_info": "[15时14分 ~ 16时02分]"
        },
        {
          "title": "OpenAI至少从编码初创公司Cline招聘了七名员工。",
          "url": "https://flash.jin10.com/detail/20260129071311535800",
          "source": "金十数据",
          "ranks": [
            9
          ],
          "is_new": false,
          "appearance_count": 2,
          "time_info": "[07时27分 ~ 07时50分]"
        },
        {
          "title": "财联社1月29日电，英伟达CEO黄仁勋表示，非常愿意投资OpenAI。",
          "url": "https://api3.cls.cn/share/article/2273864?os=web&sv=8.4.6&app=CailianpressWeb",
          "source": "财联社电报",
          "ranks": [
            13
          ],
          "is_new": false,
          "appearance_count": 1,
          "time_info": "14时07分"
        },
        {
          "title": "英伟达、微软和亚马逊正在商谈向OpenAI投资约600亿美元。亚马逊或将扩大与OpenAI的云服务器租赁协议。（The Information）",
          "url": "https://wallstreetcn.com/livenews/3046051",
          "source": "华尔街见闻-快讯",
          "ranks": [
            22
          ],
          "is_new": false,
          "appearance_count": 1,
          "time_info": "12时12分"
        }
      ]
    },
    {
      "keyword_group": "氢氧化锂 六氟磷酸锂 锂盐 光伏 钙钛矿",
      "match_count": 5,
      "titles": [
        {
          "title": "工信部召开光伏行业企业家座谈会，要求坚决破除行业“内卷式”竞争",
          "url": "https://wallstreetcn.com/livenews/3045906",
          "source": "华尔街见闻-快讯",
          "ranks": [
            2
          ],
          "is_new": false,
          "appearance_count": 1,
          "time_info": "07时50分"
        },
        {
          "title": "秀强股份(300160.SZ)：目前暂未针对钙钛矿领域开展专项研发",
          "url": "https://www.gelonghui.com/news/5159509",
          "source": "格隆汇",
          "ranks": [
            3
          ],
          "is_new": false,
          "appearance_count": 1,
          "time_info": "09时59分"
        },
        {
          "title": "工信部召开光伏行业企业家座谈会：坚决破除行业“内卷式”竞争",
          "url": "https://www.cls.cn/detail/2273449",
          "source": "财联社热门",
          "ranks": [
            9,
            8,
            7
          ],
          "is_new": false,
          "appearance_count": 5,
          "time_info": "[12时11分 ~ 15时14分]"
        },
        {
          "title": "中国工信部：坚决破除光伏行业内卷式竞争",
          "url": "https://www.zaochenbao.com/news/china/202601/2963514.html",
          "source": "早报",
          "ranks": [
            3,
            6
          ],
          "is_new": false,
          "appearance_count": 2,
          "time_info": "[14时07分 ~ 15时14分]"
        },
        {
          "title": "赛道路演连轴转，听众不够用了？AI、太空、光伏谁在C位？",
          "url": "https://www.cls.cn/detail/2272316",
          "source": "财联社热门",
          "ranks": [
            9
          ],
          "is_new": false,
          "appearance_count": 1,
          "time_info": "00时37分"
        }
      ]
    },
    {
      "keyword_group": "存储芯片 HBM DDR5 DDR6 DDR4 闪存",
      "match_count": 4,
      "titles": [
        {
          "title": "存储芯片概念反复活跃 恒烁股份涨超11%",
          "url": "https://api3.cls.cn/share/article/2273594?os=web&sv=8.4.6&app=CailianpressWeb",
          "source": "财联社电报",
          "ranks": [
            5
          ],
          "is_new": false,
          "appearance_count": 1,
          "time_info": "09时59分"
        },
        {
          "title": "财联社1月29日电，三星电子称，HBM4芯片将于第一季度出货。",
          "url": "https://api3.cls.cn/share/article/2273412?os=web&sv=8.4.6&app=CailianpressWeb",
          "source": "财联社电报",
          "ranks": [
            6
          ],
          "is_new": false,
          "appearance_count": 1,
          "time_info": "07时27分"
        },
        {
          "title": "财联社1月29日电，微软称，存储芯片涨价，将影响到云开支。",
          "url": "https://api3.cls.cn/share/article/2273429?os=web&sv=8.4.6&app=CailianpressWeb",
          "source": "财联社电报",
          "ranks": [
            11
          ],
          "is_new": false,
          "appearance_count": 1,
          "time_info": "07时50分"
        },
        {
          "title": "微软：（供应商对）存储芯片涨价，将影响到云开支。 当前季度，看到Azure销售增长37%-38%。",
          "url": "https://wallstreetcn.com/livenews/3045894",
          "source": "华尔街见闻-快讯",
          "ranks": [
            14
          ],
          "is_new": false,
          "appearance_count": 1,
          "time_info": "07时50分"
        }
      ]
    },
    {
      "keyword_group": "英特尔 高通",
      "match_count": 4,
      "titles": [
        {
          "title": "美股异动丨获公司CFO增持，英特尔大涨超10%，今年累涨超31%",
          "url": "https://www.gelonghui.com/news/5159393",
          "source": "格隆汇",
          "ranks": [
            14,
            15
          ],
          "is_new": false,
          "appearance_count": 13,
          "time_info": "[00时37分 ~ 06时55分]"
        },
        {
          "title": "美国总统特朗普在“特朗普账户”活动上感谢Gerstner、优步（Uber）、以及英特尔。",
          "url": "https://wallstreetcn.com/livenews/3045718",
          "source": "华尔街见闻-快讯",
          "ranks": [
            6,
            21
          ],
          "is_new": false,
          "appearance_count": 2,
          "time_info": "[01时33分 ~ 02时38分]"
        },
        {
          "title": "美国总统特朗普称赞优步和英特尔为“特朗普账户”捐款。",
          "url": "https://flash.jin10.com/detail/20260129004214872800",
          "source": "金十数据",
          "ranks": [
            7
          ],
          "is_new": false,
          "appearance_count": 1,
          "time_info": "01时33分"
        },
        {
          "title": "英特尔涨幅达12％。",
          "url": "https://wallstreetcn.com/livenews/3045796",
          "source": "华尔街见闻-快讯",
          "ranks": [
            18
          ],
          "is_new": false,
          "appearance_count": 1,
          "time_info": "04时31分"
        }
      ]
    },
    {
      "keyword_group": "石墨负极 石墨烯 碳酸锂 多晶硅 工业硅 碳酸锂",
      "match_count": 3,
      "titles": [
        {
          "title": "财联社1月29日电，广期所品种仓单及变化如下：碳酸锂期货仓单30211手，环比上个交易日增加245手；多晶硅期货仓单8090手，环比上个交易日增加770手；工业硅期货仓单13655手，环比上个交易日增加384手。",
          "url": "https://api3.cls.cn/share/article/2274079?os=web&sv=8.4.6&app=CailianpressWeb",
          "source": "财联社电报",
          "ranks": [
            5
          ],
          "is_new": false,
          "appearance_count": 2,
          "time_info": "[16时01分 ~ 16时02分]"
        },
        {
          "title": "内盘期货多数收涨，沪银收涨逾8%，沪金涨近8%，国际铜涨7%，沪铜涨逾6%，燃油涨4%，焦煤、原油、沥青、焦炭、低硫燃油涨逾3%；多晶硅收跌逾4%，碳酸锂跌逾3%。",
          "url": "https://wallstreetcn.com/livenews/3046206",
          "source": "华尔街见闻-快讯",
          "ranks": [
            12,
            29
          ],
          "is_new": false,
          "appearance_count": 2,
          "time_info": "[15时14分 ~ 16时02分]"
        },
        {
          "title": "早盘收盘，国内期货主力合约大面积飘红，沪金涨超7%，沪铜、国际铜涨超6%，沪银涨近6%，燃油涨超4%，SC原油、低硫燃料油（LU）、沪铝涨超3%，沥青、沪锌涨近3%，钯、橡胶、20号胶、铂、焦炭涨超2%。跌幅方面，多晶硅跌近3%，碳酸锂跌超1%。",
          "url": "https://flash.jin10.com/detail/20260129113115255800",
          "source": "金十数据",
          "ranks": [
            15
          ],
          "is_new": false,
          "appearance_count": 2,
          "time_info": "[12时11分 ~ 12时12分]"
        }
      ]
    },
    {
      "keyword_group": "储能",
      "match_count": 2,
      "titles": [
        {
          "title": "南网储能：预计2025年净利润同比增加47.98%-53.31%",
          "url": "https://wallstreetcn.com/livenews/3046242",
          "source": "华尔街见闻-快讯",
          "ranks": [
            7
          ],
          "is_new": true,
          "appearance_count": 1,
          "time_info": "16时02分"
        },
        {
          "title": "LG新能源瞄准数据中心储能需求 以对冲电动汽车市场低迷",
          "url": "https://flash.jin10.com/detail/20260129124738924800",
          "source": "金十数据",
          "ranks": [
            27
          ],
          "is_new": false,
          "appearance_count": 1,
          "time_info": "13时29分"
        }
      ]
    },
    {
      "keyword_group": "低空经济 eVTOL",
      "match_count": 2,
      "titles": [
        {
          "title": "德迈仕(301007.SZ)：公司暂无产品用于低空经济领域",
          "url": "https://www.gelonghui.com/news/5160261",
          "source": "格隆汇",
          "ranks": [
            3
          ],
          "is_new": false,
          "appearance_count": 2,
          "time_info": "[16时01分 ~ 16时02分]"
        },
        {
          "title": "德赛电池(000049.SZ)：公司正积极探索锂电池相关产品在新型智能终端、低空经济等前沿场景的应用机会",
          "url": "https://www.gelonghui.com/news/5159552",
          "source": "格隆汇",
          "ranks": [
            10
          ],
          "is_new": false,
          "appearance_count": 1,
          "time_info": "13时29分"
        }
      ]
    },
    {
      "keyword_group": "苹果 比亚迪",
      "match_count": 2,
      "titles": [
        {
          "title": "苹果CEO库克：明尼阿波利斯事件令我心碎，已与特朗普沟通",
          "url": "https://wallstreetcn.com/livenews/3045721",
          "source": "华尔街见闻-快讯",
          "ranks": [
            3,
            18
          ],
          "is_new": false,
          "appearance_count": 2,
          "time_info": "[01时33分 ~ 02时38分]"
        },
        {
          "title": "分析师：苹果公司的AI路线图仍是投资者最关心的问题",
          "url": "https://wallstreetcn.com/livenews/3045749",
          "source": "华尔街见闻-快讯",
          "ranks": [
            12,
            22
          ],
          "is_new": false,
          "appearance_count": 2,
          "time_info": "[03时28分 ~ 03时53分]"
        }
      ]
    },
    {
      "keyword_group": "液冷",
      "match_count": 1,
      "titles": [
        {
          "title": "博杰股份(002975.SZ)：公司液冷测试设备有供货给N客户等",
          "url": "https://www.gelonghui.com/news/5159502",
          "source": "格隆汇",
          "ranks": [
            10
          ],
          "is_new": false,
          "appearance_count": 1,
          "time_info": "09时59分"
        }
      ]
    },
    {
      "keyword_group": "消费电子 智能穿戴 智能座舱",
      "match_count": 1,
      "titles": [
        {
          "title": "新技术催生新动能，18家消费电子公司2025年业绩预盈",
          "url": "https://wallstreetcn.com/livenews/3045879",
          "source": "华尔街见闻-快讯",
          "ranks": [
            9,
            28
          ],
          "is_new": false,
          "appearance_count": 2,
          "time_info": "[07时27分 ~ 07时50分]"
        }
      ]
    },
    {
      "keyword_group": "新材料 碳化硅 液态金属 气凝胶 钴酸锂",
      "match_count": 1,
      "titles": [
        {
          "title": "【研选】中国石油集团2026年工作会议召开，提出发挥能源保供“顶梁柱”作用，分析师看好受益于中国石油集团的一体化全产业链优势公司；公司积极布局新材料，且直接受益涤纶工业丝价差同比修复",
          "url": "https://api3.cls.cn/share/article/2272169?os=web&sv=8.4.6&app=CailianpressWeb",
          "source": "财联社电报",
          "ranks": [
            9
          ],
          "is_new": false,
          "appearance_count": 1,
          "time_info": "07时27分"
        }
      ]
    },
    {
      "keyword_group": "脑机接口 脑工程 脑科学 神经接口 植入式电极 非侵入式脑电",
      "match_count": 1,
      "titles": [
        {
          "title": "马斯克：新一代神经链接脑机接口增强版的性能将提升至三倍",
          "url": "https://api3.cls.cn/share/article/2273338?os=web&sv=8.4.6&app=CailianpressWeb",
          "source": "财联社电报",
          "ranks": [
            4,
            9,
            15
          ],
          "is_new": false,
          "appearance_count": 4,
          "time_info": "[02时37分 ~ 03时53分]"
        }
      ]
    },
    {
      "keyword_group": "比特币 以太坊",
      "match_count": 1,
      "titles": [
        {
          "title": "“新债王”Gundlach：相比私人市场，我更青睐于公开市场。 没有对我自己的投资组合做出任何调整。 美元不像是一种避险货币。 避险似乎属于明确的资产，比特币不是。",
          "url": "https://wallstreetcn.com/livenews/3045815",
          "source": "华尔街见闻-快讯",
          "ranks": [
            14,
            25
          ],
          "is_new": false,
          "appearance_count": 2,
          "time_info": "[05时29分 ~ 05时56分]"
        }
      ]
    }
  ],
  "report_image_url": "https://joyce677.github.io/TrendRadar/img/news.jpg"
}